funcnodes_chemprop/__init__.py
funcnodes_chemprop/functions.py
funcnodes_chemprop-0.1.3.dist-info/licenses/LICENSE
funcnodes_chemprop-0.1.3.dist-info/METADATA
funcnodes_chemprop-0.1.3.dist-info/WHEEL
funcnodes_chemprop-0.1.3.dist-info/entry_points.txt
funcnodes_chemprop-0.1.3.dist-info/top_level.txt
funcnodes_chemprop-0.1.3.dist-info/RECORD
