Metadata-Version: 2.4
Name: funcnodes-chemprop
Version: 0.1.3
Author-email: Julian Kimmig <julian.kimmig@gmx.net>
License: AGPL-3.0
Requires-Python: <3.13,>=3.11
License-File: LICENSE
Requires-Dist: funcnodes-pandas
Requires-Dist: chemprop
Requires-Dist: funcnodes
Requires-Dist: funcnodes-plotly
Dynamic: license-file
